lfuncs/__init__.py
example_lfuncs-0.1.dist-info/LICENSE
example_lfuncs-0.1.dist-info/METADATA
example_lfuncs-0.1.dist-info/WHEEL
example_lfuncs-0.1.dist-info/top_level.txt
example_lfuncs-0.1.dist-info/RECORD
