Metadata-Version: 2.1
Name: example-lfuncs
Version: 0.1
Summary: A few functions to teach Python and PIP
Home-page: https://github.com/diging-training/example-package-lfuncs
Author: jdamerow
Author-email: jdamerow@asu.edu
License: UNKNOWN
Platform: UNKNOWN
Classifier: Programming Language :: Python :: 3
Classifier: License :: OSI Approved :: Mozilla Public License 2.0 (MPL 2.0)
Classifier: Operating System :: OS Independent
Requires-Python: >=3.6
